[
  [
    {
      "id": "9b49",
      "nome": "araruna",
      "urlImg": "https://encrypted-tbn0.gstatic.com/images?q=tbn:ANd9GcRXRTUYWExSEl6GJf_PF1bG2iMMGFh9ChkNeQ&s",
      "desc": "bonito"
    },
    {
      "id": "5e7e",
      "nome": "centro cultural de sao francsico",
      "urlImg": "https://imgmd.net/images/v1/guia/2663196/centro-cultural-sao-francisco.jpg",
      "desc": "interessante"
    },
    {
      "id": "86bd",
      "nome": "farol de cabo branco",
      "urlImg": "https://upload.wikimedia.org/wikipedia/commons/e/eb/Joao_Pessoa_Paraiba_Farol_do_Cabo_Branco2.jpg",
      "desc": "bonito"
    }
  ]
]